sigbox/__init__.py
sigbox/global_signal_box.py
sigbox/sigbox.py
sigbox/signal.py
sigbox/signal_box.py
sigbox/signal_data.py
sigbox/signal_decorator.py
sigbox-0.1a0.dist-info/LICENSE
sigbox-0.1a0.dist-info/METADATA
sigbox-0.1a0.dist-info/WHEEL
sigbox-0.1a0.dist-info/top_level.txt
sigbox-0.1a0.dist-info/RECORD
